my_utils/__init__.py
my_utils/converter_utils.py
my_utils/text_utils.py
MoreUtilspy-0.13.dist-info/LICENSE
MoreUtilspy-0.13.dist-info/METADATA
MoreUtilspy-0.13.dist-info/WHEEL
MoreUtilspy-0.13.dist-info/top_level.txt
MoreUtilspy-0.13.dist-info/RECORD
