Metadata-Version: 2.1
Name: MoreUtilspy
Version: 0.13
Summary: a package containing more utilities for python
Author: oussama errafif
Author-email: oussamaerra2002@gmail.com
Keywords: python,utils
Classifier: Development Status :: 1 - Planning
Classifier: Intended Audience :: Developers
Classifier: Programming Language :: Python :: 3
Classifier: Operating System :: Unix
Classifier: Operating System :: MacOS :: MacOS X
Classifier: Operating System :: Microsoft :: Windows
License-File: LICENSE
Requires-Dist: csv
Requires-Dist: random
Requires-Dist: string
Requires-Dist: json
Requires-Dist: re
Requires-Dist: datetime
Requires-Dist: math
